json_dunder/__init__.py
json_dunder/json_dunder.py
json_dunder-0.0.0.dist-info/LICENSE
json_dunder-0.0.0.dist-info/METADATA
json_dunder-0.0.0.dist-info/WHEEL
json_dunder-0.0.0.dist-info/top_level.txt
json_dunder-0.0.0.dist-info/RECORD
