Metadata-Version: 2.1
Name: json_dunder
Version: 0.0.0
Summary: Encode objects with a __json__ dunder method and decode objects with a __from_json__ dunder method.
Home-page: https://github.com/justengel/json_dunder
Download-URL: https://github.com/justengel/json_dunder/archive/refs/tags/v0.0.0.tar.gz
Author: Justin Engel
Author-email: jtengel08@gmail.com
License: Proprietary
Keywords: json decoder encoder dunder
Platform: any
Classifier: Programming Language :: Python
Classifier: Programming Language :: Python :: 3
Classifier: Operating System :: OS Independent
License-File: LICENSE
